tabbyj/__main__.py
tabbyj-0.2.2.dist-info/entry_points.txt
tabbyj-0.2.2.dist-info/LICENSE
tabbyj-0.2.2.dist-info/WHEEL
tabbyj-0.2.2.dist-info/METADATA
tabbyj-0.2.2.dist-info/RECORD
